Robson/__init__.py
Robson/__main__.py
Robson/robson.py
Robson/templates/Java Template.zip
robotframework_robson-1.0.3.dist-info/entry_points.txt
robotframework_robson-1.0.3.dist-info/LICENSE
robotframework_robson-1.0.3.dist-info/WHEEL
robotframework_robson-1.0.3.dist-info/METADATA
robotframework_robson-1.0.3.dist-info/RECORD
