Metadata-Version: 2.1
Name: robotframework-robson
Version: 1.0.3
Summary: JSON-RPC-based dynamic library interface for Robot Framework
Author-email: Marduk Bolaños <marduk.bolanos@imbus.de>
Requires-Python: >=3.7
Requires-Dist: robotframework>=6.0
Requires-Dist: typing-extensions>=4.7.0
Requires-Dist: click>=8.0.4
Project-URL: homepage, https://github.com/mardukbp/robotframework-robson
